byted_overpass_caijing_doupay_channel_admin/__init__.py
byted_overpass_caijing_doupay_channel_admin-0.0.1.dist-info/METADATA
byted_overpass_caijing_doupay_channel_admin-0.0.1.dist-info/WHEEL
byted_overpass_caijing_doupay_channel_admin-0.0.1.dist-info/top_level.txt
byted_overpass_caijing_doupay_channel_admin-0.0.1.dist-info/RECORD
